{
  "generator-jhipster": {
    "authenticationType": "jwt",
    "cacheProvider": "ehcache",
    "clientFramework": "angularX",
    "serverPort": "8080",
    "serviceDiscoveryType": false,
    "skipUserManagement": false,
    "withAdminUi": true,
    "baseName": "PowerTrainer",
    "buildTool": "maven",
    "databaseType": "sql",
    "devDatabaseType": "h2Disk",
    "enableHibernateCache": true,
    "enableSwaggerCodegen": true,
    "enableTranslation": true,
    "jhiPrefix": "jhi",
    "languages": ["en", "it"],
    "messageBroker": false,
    "prodDatabaseType": "postgresql",
    "searchEngine": false,
    "skipClient": false,
    "testFrameworks": [],
    "websocket": false,
    "applicationType": "monolith",
    "blueprints": [],
    "clientPackageManager": "npm",
    "clientTheme": "materia",
    "clientThemeVariant": "primary",
    "creationTimestamp": 1617382260009,
    "dtoSuffix": "DTO",
    "jhipsterVersion": "7.0.1",
    "jwtSecretKey": "MjUyNTY4OTViZjZlOTMyZGM5YWNhNGI2ZjQxNDVlMzVjZDA1YjcyOWNhNjQ1Yzg1OGQ4NjM5YTk2MzA2MmYzM2ZlZmVjOTExNTU1ZmIyYThlZWJlZjY5YzlmMWYwOGJjMmY5MGJmYmNjNzk0MjQ0YjVkMzM5MDEwMmExZjE2MjM=",
    "nativeLanguage": "en",
    "otherModules": [],
    "packageName": "com.abubusoft.powertrainer",
    "packageFolder": "com/abubusoft/powertrainer",
    "reactive": false,
    "skipServer": false,
    "entitySuffix": "",
    "entities": [
      "Calendar",
      "Exercise",
      "ExerciseValue",
      "MeasureValue",
      "MeasureType",
      "WorkoutSheet",
      "WorkoutSheetExercise",
      "Workout",
      "Muscle2Exercise",
      "WorkoutStep",
      "Device",
      "Muscle",
      "Note"
    ],
    "skipCheckLengthOfIdentifier": false,
    "skipFakeData": false,
    "pages": [],
    "lastLiquibaseTimestamp": 1617383040000
  }
}
